LICENSE
MANIFEST.in
README.md
setup.py
csrc/dp_core.cpp
galvatron/__init__.py
galvatron/core/__init__.py
galvatron/core/arguments.py
galvatron/core/profiler/__init__.py
galvatron/core/profiler/arguments.py
galvatron/core/profiler/base_profiler.py
galvatron/core/profiler/hardware_profiler.py
galvatron/core/profiler/model_profiler.py
galvatron/core/profiler/runtime_profiler.py
galvatron/core/profiler/utils.py
galvatron/core/runtime/__init__.py
galvatron/core/runtime/arguments.py
galvatron/core/runtime/comm_groups.py
galvatron/core/runtime/dataloader.py
galvatron/core/runtime/hybrid_parallel_config.py
galvatron/core/runtime/hybrid_parallel_model.py
galvatron/core/runtime/initialize.py
galvatron/core/runtime/parallel.py
galvatron/core/runtime/redistribute.py
galvatron/core/runtime/utils.py
galvatron/core/runtime/pipeline/__init__.py
galvatron/core/runtime/pipeline/grad_reduce.py
galvatron/core/runtime/pipeline/pipeline.py
galvatron/core/runtime/pipeline/sp_grad_reduce.py
galvatron/core/runtime/pipeline/utils.py
galvatron/core/runtime/tensor_parallel/__init__.py
galvatron/core/runtime/tensor_parallel/reset.py
galvatron/core/runtime/tensor_parallel/transformer.py
galvatron/core/runtime/tensor_parallel/utils.py
galvatron/core/search_engine/__init__.py
galvatron/core/search_engine/arguments.py
galvatron/core/search_engine/cost_model.py
galvatron/core/search_engine/cost_model_args.py
galvatron/core/search_engine/dynamic_programming.py
galvatron/core/search_engine/search_engine.py
galvatron/core/search_engine/utils.py
galvatron/models/__init__.py
galvatron/models/T5/T5Model_checkpoint.py
galvatron/models/T5/T5Model_hybrid_parallel.py
galvatron/models/T5/T5Model_sequential.py
galvatron/models/T5/T5Model_tensor_parallel.py
galvatron/models/T5/__init__.py
galvatron/models/T5/arguments.py
galvatron/models/T5/dataloader.py
galvatron/models/T5/profiler.py
galvatron/models/T5/search_dist.py
galvatron/models/T5/train_dist.py
galvatron/models/T5/train_dist_random.py
hetu_galvatron.egg-info/PKG-INFO
hetu_galvatron.egg-info/SOURCES.txt
hetu_galvatron.egg-info/dependency_links.txt
hetu_galvatron.egg-info/requires.txt
hetu_galvatron.egg-info/top_level.txt
