Metadata-Version: 2.1
Name: hetu-galvatron
Version: 2.4.0
Summary: Galvatron, a Efficient Transformer Training Framework for Multiple GPUs Using Automatic Parallelism
Author: Xinyi Liu, Yujie Wang, Shenhan Zhu
Author-email: xy.liu@stu.pku.edu.cn, alfredwang@pku.edu.cn, shenhan.zhu@pku.edu.cn
Requires-Python: >=3.8
License-File: LICENSE
Requires-Dist: torch>=2.0.1
Requires-Dist: torchvision>=0.15.2
Requires-Dist: transformers>=4.31.0
Requires-Dist: h5py>=3.6.0
Requires-Dist: attrs>=21.4.0
Requires-Dist: yacs>=0.1.8
Requires-Dist: six>=1.15.0
Requires-Dist: sentencepiece>=0.1.95
Requires-Dist: pybind11>=2.9.1
Requires-Dist: scipy>=1.10.1
